{
  "custom": {
    "deviceDescription": null,
    "deviceTagPath": "Domestic/Precinct/Domestic SPS/Street Lights",
    "lightControl": false,
    "siteName": null,
    "sitePath": "Domestic/Precinct/Domestic SPS",
    "subArea": null
  },
  "params": {
    "deviceName": "Street Lights",
    "deviceParentPath": "Domestic/Precinct/Domestic SPS"
  },
  "propConfig": {
    "custom.deviceDescription": {
      "binding": {
        "config": {
          "fallbackDelay": 2.5,
          "mode": "indirect",
          "references": {
            "deviceTagPath": "{view.custom.deviceTagPath}"
          },
          "tagPath": "{deviceTagPath}/Parameters.DeviceName"
        },
        "transforms": [
          {
            "expression": "replace({value}, \"Domestic\", \"\")",
            "type": "expression"
          }
        ],
        "type": "tag"
      },
      "persistent": true
    },
    "custom.deviceTagPath": {
      "binding": {
        "config": {
          "expression": "{view.params.deviceParentPath} + \u0027/\u0027 +\r\n{view.params.deviceName}"
        },
        "type": "expr"
      },
      "persistent": true
    },
    "custom.siteName": {
      "binding": {
        "config": {
          "fallbackDelay": 2.5,
          "mode": "indirect",
          "references": {
            "deviceTagPath": "{view.custom.deviceTagPath}"
          },
          "tagPath": "{deviceTagPath}/Parameters/Alarm_ParentDevice"
        },
        "type": "tag"
      },
      "persistent": true
    },
    "custom.sitePath": {
      "binding": {
        "config": {
          "expression": "{view.params.deviceParentPath}"
        },
        "type": "expr"
      },
      "persistent": true
    },
    "custom.subArea": {
      "binding": {
        "config": {
          "fallbackDelay": 2.5,
          "mode": "indirect",
          "references": {
            "deviceTagPath": "{view.custom.deviceTagPath}"
          },
          "tagPath": "{deviceTagPath}/Parameters/Alarm_Area"
        },
        "type": "tag"
      },
      "persistent": true
    },
    "params.deviceName": {
      "paramDirection": "input",
      "persistent": true
    },
    "params.deviceParentPath": {
      "paramDirection": "input",
      "persistent": true
    }
  },
  "props": {
    "defaultSize": {
      "height": 490,
      "width": 371
    }
  },
  "root": {
    "children": [
      {
        "children": [
          {
            "children": [
              {
                "children": [
                  {
                    "meta": {
                      "name": "Label_1"
                    },
                    "position": {
                      "grow": 1
                    },
                    "propConfig": {
                      "props.text": {
                        "binding": {
                          "config": {
                            "expression": "{view.custom.siteName}"
                          },
                          "type": "expr"
                        }
                      }
                    },
                    "props": {
                      "style": {
                        "color": "var(--neutral-20)",
                        "fontSize": "12pt",
                        "fontWeight": "bold",
                        "letterSpacing": "1px",
                        "overflow": "hidden",
                        "textAlign": "center",
                        "textTransform": "uppercase"
                      }
                    },
                    "type": "ia.display.label"
                  },
                  {
                    "meta": {
                      "name": "Label_0"
                    },
                    "position": {
                      "grow": 1,
                      "shrink": 0
                    },
                    "propConfig": {
                      "props.text": {
                        "binding": {
                          "config": {
                            "expression": "{view.custom.subArea} + \u0027 - \u0027 + {view.custom.deviceDescription}"
                          },
                          "type": "expr"
                        }
                      }
                    },
                    "props": {
                      "style": {
                        "color": "var(--neutral-20)",
                        "fontSize": "10pt",
                        "fontStyle": "italic",
                        "fontWeight": "lighter",
                        "letterSpacing": "1px",
                        "marginBottom": "5px",
                        "overflow": "hidden",
                        "textAlign": "center",
                        "textTransform": "uppercase"
                      }
                    },
                    "type": "ia.display.label"
                  }
                ],
                "meta": {
                  "name": "FlexContainer"
                },
                "position": {
                  "grow": 1,
                  "shrink": 0
                },
                "props": {
                  "direction": "column",
                  "style": {
                    "overflow": "hidden"
                  }
                },
                "type": "ia.container.flex"
              },
              {
                "children": [
                  {
                    "meta": {
                      "name": "Alarm Icon"
                    },
                    "position": {
                      "height": 38,
                      "width": 38,
                      "x": 1,
                      "y": 1
                    },
                    "propConfig": {
                      "props.params.alarmSummary.parentPath": {
                        "binding": {
                          "config": {
                            "path": "view.custom.deviceTagPath"
                          },
                          "type": "property"
                        }
                      }
                    },
                    "props": {
                      "params": {
                        "alarmSummary": {
                          "enabled": true
                        },
                        "device": {
                          "deviceName": "",
                          "deviceParentPath": "",
                          "enabled": false
                        }
                      },
                      "path": "Shared/Alarms/Symbol",
                      "style": {
                        "overflow": "hidden"
                      }
                    },
                    "type": "ia.display.view"
                  }
                ],
                "events": {
                  "dom": {
                    "onClick": {
                      "config": {
                        "script": "\tself.parent.parent.parent.getChild(\"Body\").getChild(\"details_expanded\").position.display \u003d False\n\tself.parent.parent.parent.getChild(\"Body\").getChild(\"trend_expanded\").position.display \u003d False\n\tself.parent.parent.parent.getChild(\"Body\").getChild(\"alarms_expanded\").position.display \u003d True"
                      },
                      "scope": "G",
                      "type": "script"
                    }
                  }
                },
                "meta": {
                  "name": "Alarm Button"
                },
                "position": {
                  "basis": "40px",
                  "shrink": 0
                },
                "propConfig": {
                  "position.display": {
                    "binding": {
                      "config": {
                        "fallbackDelay": 2.5,
                        "mode": "indirect",
                        "references": {
                          "deviceTagPath": "{view.custom.deviceTagPath}"
                        },
                        "tagPath": "{deviceTagPath}/Alarm Summary/Priority Counts/Active"
                      },
                      "transforms": [
                        {
                          "code": "\tif \tvalue \u003e 0:\n\t\tvalue \u003d 1\n\telse:\n\t\tvalue \u003d 0\n\t\t\n\treturn value",
                          "type": "script"
                        }
                      ],
                      "type": "tag"
                    }
                  }
                },
                "props": {
                  "style": {
                    "cursor": "pointer",
                    "marginBottom": 3,
                    "marginRight": 5,
                    "marginTop": 3,
                    "overflow": "hidden"
                  }
                },
                "type": "ia.container.coord"
              }
            ],
            "meta": {
              "name": "FlexContainer"
            },
            "position": {
              "basis": "0px",
              "grow": 1,
              "shrink": 0
            },
            "props": {
              "style": {
                "overflow": "hidden"
              }
            },
            "type": "ia.container.flex"
          }
        ],
        "meta": {
          "name": "Header"
        },
        "position": {
          "shrink": 0
        },
        "propConfig": {
          "custom.key": {
            "binding": {
              "config": {
                "path": "view.custom.deviceTagPath"
              },
              "type": "property"
            }
          }
        },
        "props": {
          "style": {
            "backgroundColor": "var(--neutral-90)",
            "borderBottomColor": "var(--neutral-100)",
            "borderBottomStyle": "solid",
            "borderBottomWidth": "1px",
            "overflow": "hidden"
          }
        },
        "type": "ia.container.flex"
      },
      {
        "children": [
          {
            "children": [
              {
                "children": [
                  {
                    "children": [
                      {
                        "meta": {
                          "name": "Heading"
                        },
                        "position": {
                          "grow": 1,
                          "shrink": 0
                        },
                        "props": {
                          "style": {
                            "overflow": "hidden",
                            "textAlign": "left"
                          }
                        },
                        "type": "ia.display.label"
                      }
                    ],
                    "meta": {
                      "name": "FlexContainer_0"
                    },
                    "position": {
                      "basis": "50px",
                      "grow": 1
                    },
                    "props": {
                      "style": {
                        "overflow": "hidden"
                      }
                    },
                    "type": "ia.container.flex"
                  },
                  {
                    "meta": {
                      "name": "Heading"
                    },
                    "position": {
                      "shrink": 0
                    },
                    "props": {
                      "style": {
                        "overflow": "hidden",
                        "textAlign": "left"
                      },
                      "text": "control"
                    },
                    "type": "ia.display.label"
                  },
                  {
                    "meta": {
                      "name": "Label_0"
                    },
                    "position": {
                      "basis": "26px",
                      "grow": 1
                    },
                    "props": {
                      "style": {
                        "overflow": "hidden"
                      }
                    },
                    "type": "ia.display.label"
                  },
                  {
                    "meta": {
                      "name": "Icon"
                    },
                    "position": {
                      "basis": "24px",
                      "shrink": 0
                    },
                    "propConfig": {
                      "props.path": {
                        "binding": {
                          "config": {
                            "path": ".../control_expanded.position.display"
                          },
                          "transforms": [
                            {
                              "fallback": null,
                              "inputType": "scalar",
                              "mappings": [
                                {
                                  "input": false,
                                  "output": "material/keyboard_arrow_up"
                                },
                                {
                                  "input": true,
                                  "output": "material/keyboard_arrow_down"
                                }
                              ],
                              "outputType": "scalar",
                              "type": "map"
                            }
                          ],
                          "type": "property"
                        }
                      }
                    },
                    "props": {
                      "style": {
                        "overflow": "hidden"
                      }
                    },
                    "type": "ia.display.icon"
                  }
                ],
                "events": {
                  "dom": {
                    "onClick": {
                      "config": {
                        "script": "\tpanelName \u003d self.getChild(\"Heading\").props.text + \u0027_expanded\u0027\n\tpanelName \u003d panelName.lower()\n\t\n\tself.getSibling(panelName).position.display \u003d not self.getSibling(panelName).position.display"
                      },
                      "scope": "G",
                      "type": "script"
                    }
                  }
                },
                "meta": {
                  "name": "control_header"
                },
                "position": {
                  "basis": "40px",
                  "shrink": 0
                },
                "propConfig": {
                  "position.display": {
                    "binding": {
                      "config": {
                        "path": "view.custom.lightControl"
                      },
                      "enabled": false,
                      "type": "property"
                    }
                  }
                },
                "props": {
                  "style": {
                    "classes": "UI/Text/Heading1",
                    "cursor": "pointer",
                    "overflow": "hidden"
                  }
                },
                "type": "ia.container.flex"
              },
              {
                "children": [
                  {
                    "children": [
                      {
                        "meta": {
                          "name": "Circuit"
                        },
                        "position": {
                          "basis": "90px",
                          "shrink": 0
                        },
                        "props": {
                          "style": {
                            "classes": "UI/Text/Heading3",
                            "overflow": "hidden",
                            "textAlign": "left"
                          },
                          "text": "Lights"
                        },
                        "type": "ia.display.label"
                      },
                      {
                        "meta": {
                          "name": "Status"
                        },
                        "position": {
                          "basis": "110px",
                          "shrink": 0
                        },
                        "props": {
                          "style": {
                            "classes": "UI/Text/Heading3",
                            "overflow": "hidden",
                            "textAlign": "center"
                          },
                          "text": "Status"
                        },
                        "type": "ia.display.label"
                      },
                      {
                        "meta": {
                          "name": "Control"
                        },
                        "position": {
                          "basis": "161px",
                          "shrink": 0
                        },
                        "props": {
                          "style": {
                            "classes": "UI/Text/Heading3",
                            "overflow": "hidden",
                            "textAlign": "center"
                          },
                          "text": "Control"
                        },
                        "type": "ia.display.label"
                      }
                    ],
                    "events": {
                      "dom": {
                        "onClick": {
                          "config": {
                            "script": "\tpanelName \u003d self.getChild(\"Heading\").props.text + \u0027_expanded\u0027\n\tpanelName \u003d panelName.lower()\n\t\n\tself.getSibling(panelName).position.display \u003d not self.getSibling(panelName).position.display"
                          },
                          "scope": "G",
                          "type": "script"
                        }
                      }
                    },
                    "meta": {
                      "name": "control_header"
                    },
                    "position": {
                      "basis": "40px",
                      "shrink": 0
                    },
                    "props": {
                      "style": {
                        "classes": "UI/Text/Heading2",
                        "cursor": "pointer",
                        "overflow": "hidden"
                      }
                    },
                    "type": "ia.container.flex"
                  },
                  {
                    "children": [
                      {
                        "children": [
                          {
                            "meta": {
                              "name": "Label"
                            },
                            "position": {
                              "basis": "50px"
                            },
                            "props": {
                              "style": {
                                "overflow": "hidden"
                              },
                              "text": "Roadway"
                            },
                            "type": "ia.display.label"
                          },
                          {
                            "meta": {
                              "name": "Label_0"
                            },
                            "position": {
                              "basis": "50px"
                            },
                            "props": {
                              "style": {
                                "overflow": "hidden"
                              },
                              "text": "Ballustrade"
                            },
                            "type": "ia.display.label"
                          },
                          {
                            "meta": {
                              "name": "Label_1"
                            },
                            "position": {
                              "basis": "50px"
                            },
                            "props": {
                              "style": {
                                "overflow": "hidden"
                              },
                              "text": "Awning"
                            },
                            "type": "ia.display.label"
                          }
                        ],
                        "meta": {
                          "name": "FlexContainer"
                        },
                        "position": {
                          "basis": "90px"
                        },
                        "props": {
                          "direction": "column"
                        },
                        "type": "ia.container.flex"
                      },
                      {
                        "children": [
                          {
                            "meta": {
                              "name": "Label"
                            },
                            "position": {
                              "basis": "50px"
                            },
                            "propConfig": {
                              "props.text": {
                                "binding": {
                                  "config": {
                                    "expression": "binEnc(tag({view.custom.deviceTagPath}+\u0027/Lights/Light Circuit 1/Status/Contactor 1 On\u0027),tag({view.custom.deviceTagPath}+\u0027/Lights/Light Circuit 1/Status/Contactor 2 On\u0027))"
                                  },
                                  "transforms": [
                                    {
                                      "fallback": null,
                                      "inputType": "scalar",
                                      "mappings": [
                                        {
                                          "input": 0,
                                          "output": "Off"
                                        },
                                        {
                                          "input": 1,
                                          "output": "Group A - 50%"
                                        },
                                        {
                                          "input": 2,
                                          "output": "Group B - 50%"
                                        },
                                        {
                                          "input": 3,
                                          "output": "100%"
                                        }
                                      ],
                                      "outputType": "scalar",
                                      "type": "map"
                                    }
                                  ],
                                  "type": "expr"
                                }
                              }
                            },
                            "props": {
                              "textStyle": {
                                "textAlign": "center"
                              }
                            },
                            "type": "ia.display.label"
                          },
                          {
                            "meta": {
                              "name": "Label_0"
                            },
                            "position": {
                              "basis": "50px"
                            },
                            "propConfig": {
                              "props.text": {
                                "binding": {
                                  "config": {
                                    "expression": "if(tag({view.custom.deviceTagPath}+\u0027/Lights/Light Circuit 2/Status/Contactor 1 On\u0027),\u0027On\u0027,\u0027Off\u0027)"
                                  },
                                  "type": "expr"
                                }
                              }
                            },
                            "props": {
                              "style": {
                                "textAlign": "center"
                              }
                            },
                            "type": "ia.display.label"
                          },
                          {
                            "meta": {
                              "name": "Label_1"
                            },
                            "position": {
                              "basis": "50px"
                            },
                            "propConfig": {
                              "props.text": {
                                "binding": {
                                  "config": {
                                    "expression": "if(tag({view.custom.deviceTagPath}+\u0027/Lights/Light Circuit 3/Status/Contactor 1 On\u0027),\u0027On\u0027,\u0027Off\u0027)"
                                  },
                                  "type": "expr"
                                }
                              }
                            },
                            "props": {
                              "textStyle": {
                                "textAlign": "center"
                              }
                            },
                            "type": "ia.display.label"
                          }
                        ],
                        "meta": {
                          "name": "FlexContainer_0"
                        },
                        "position": {
                          "basis": "110px"
                        },
                        "props": {
                          "direction": "column"
                        },
                        "type": "ia.container.flex"
                      },
                      {
                        "children": [
                          {
                            "children": [
                              {
                                "meta": {
                                  "name": "Single Tag"
                                },
                                "position": {
                                  "basis": "320px"
                                },
                                "propConfig": {
                                  "props.params.tagParentPath": {
                                    "binding": {
                                      "config": {
                                        "expression": "{view.custom.deviceTagPath} + \u0027/Lights/Light Circuit 1/Control\u0027"
                                      },
                                      "type": "expr"
                                    }
                                  }
                                },
                                "props": {
                                  "params": {
                                    "buttonText": "Off",
                                    "tagName": "Off Command",
                                    "writeValue": true
                                  },
                                  "path": "Shared/Templates/Display/Alexandrina/Control/Buttons/Single Tag"
                                },
                                "type": "ia.display.view"
                              },
                              {
                                "meta": {
                                  "name": "Single Tag_0"
                                },
                                "position": {
                                  "basis": "320px"
                                },
                                "propConfig": {
                                  "props.params.tagParentPath": {
                                    "binding": {
                                      "config": {
                                        "expression": "{view.custom.deviceTagPath} + \u0027/Lights/Light Circuit 1/Control\u0027"
                                      },
                                      "type": "expr"
                                    }
                                  }
                                },
                                "props": {
                                  "params": {
                                    "buttonText": "50 %",
                                    "tagName": "50pct Command",
                                    "writeValue": true
                                  },
                                  "path": "Shared/Templates/Display/Alexandrina/Control/Buttons/Single Tag"
                                },
                                "type": "ia.display.view"
                              },
                              {
                                "meta": {
                                  "name": "Single Tag_1"
                                },
                                "position": {
                                  "basis": "320px"
                                },
                                "propConfig": {
                                  "props.params.tagParentPath": {
                                    "binding": {
                                      "config": {
                                        "expression": "{view.custom.deviceTagPath} + \u0027/Lights/Light Circuit 1/Control\u0027"
                                      },
                                      "type": "expr"
                                    }
                                  }
                                },
                                "props": {
                                  "params": {
                                    "buttonText": "100 %",
                                    "tagName": "100pct Command",
                                    "writeValue": true
                                  },
                                  "path": "Shared/Templates/Display/Alexandrina/Control/Buttons/Single Tag"
                                },
                                "type": "ia.display.view"
                              }
                            ],
                            "meta": {
                              "name": "FlexContainer"
                            },
                            "position": {
                              "basis": "50px"
                            },
                            "props": {
                              "style": {
                                "overflow": "hidden"
                              }
                            },
                            "type": "ia.container.flex"
                          },
                          {
                            "children": [
                              {
                                "meta": {
                                  "name": "Single Tag"
                                },
                                "position": {
                                  "basis": "320px"
                                },
                                "propConfig": {
                                  "props.params.tagParentPath": {
                                    "binding": {
                                      "config": {
                                        "expression": "{view.custom.deviceTagPath} + \u0027/Lights/Light Circuit 2/Control\u0027"
                                      },
                                      "type": "expr"
                                    }
                                  }
                                },
                                "props": {
                                  "params": {
                                    "buttonText": "Off",
                                    "tagName": "Off Command",
                                    "writeValue": true
                                  },
                                  "path": "Shared/Templates/Display/Alexandrina/Control/Buttons/Single Tag",
                                  "style": {
                                    "marginLeft": 13,
                                    "marginRight": 13
                                  }
                                },
                                "type": "ia.display.view"
                              },
                              {
                                "meta": {
                                  "name": "Single Tag_1"
                                },
                                "position": {
                                  "basis": "320px"
                                },
                                "propConfig": {
                                  "props.params.tagParentPath": {
                                    "binding": {
                                      "config": {
                                        "expression": "{view.custom.deviceTagPath} + \u0027/Lights/Light Circuit 2/Control\u0027"
                                      },
                                      "type": "expr"
                                    }
                                  }
                                },
                                "props": {
                                  "params": {
                                    "buttonText": "On",
                                    "tagName": "100pct Command",
                                    "writeValue": true
                                  },
                                  "path": "Shared/Templates/Display/Alexandrina/Control/Buttons/Single Tag",
                                  "style": {
                                    "marginLeft": 13,
                                    "marginRight": 13
                                  }
                                },
                                "type": "ia.display.view"
                              }
                            ],
                            "meta": {
                              "name": "FlexContainer_0"
                            },
                            "position": {
                              "basis": "50px"
                            },
                            "props": {
                              "style": {
                                "overflow": "hidden"
                              }
                            },
                            "type": "ia.container.flex"
                          },
                          {
                            "children": [
                              {
                                "meta": {
                                  "name": "Single Tag"
                                },
                                "position": {
                                  "basis": "320px"
                                },
                                "propConfig": {
                                  "props.params.tagParentPath": {
                                    "binding": {
                                      "config": {
                                        "expression": "{view.custom.deviceTagPath} + \u0027/Lights/Light Circuit 3/Control\u0027"
                                      },
                                      "type": "expr"
                                    }
                                  }
                                },
                                "props": {
                                  "params": {
                                    "buttonText": "Off",
                                    "tagName": "Off Command",
                                    "writeValue": true
                                  },
                                  "path": "Shared/Templates/Display/Alexandrina/Control/Buttons/Single Tag",
                                  "style": {
                                    "marginLeft": 13,
                                    "marginRight": 13
                                  }
                                },
                                "type": "ia.display.view"
                              },
                              {
                                "meta": {
                                  "name": "Single Tag_1"
                                },
                                "position": {
                                  "basis": "320px"
                                },
                                "propConfig": {
                                  "props.params.tagParentPath": {
                                    "binding": {
                                      "config": {
                                        "expression": "{view.custom.deviceTagPath} + \u0027/Lights/Light Circuit 3/Control\u0027"
                                      },
                                      "type": "expr"
                                    }
                                  }
                                },
                                "props": {
                                  "params": {
                                    "buttonText": "On",
                                    "tagName": "100pct Command",
                                    "writeValue": true
                                  },
                                  "path": "Shared/Templates/Display/Alexandrina/Control/Buttons/Single Tag",
                                  "style": {
                                    "marginLeft": 13,
                                    "marginRight": 13
                                  }
                                },
                                "type": "ia.display.view"
                              }
                            ],
                            "meta": {
                              "name": "FlexContainer_1"
                            },
                            "position": {
                              "basis": "50px"
                            },
                            "props": {
                              "style": {
                                "overflow": "hidden"
                              }
                            },
                            "type": "ia.container.flex"
                          }
                        ],
                        "meta": {
                          "name": "FlexContainer_1"
                        },
                        "position": {
                          "basis": "161px"
                        },
                        "props": {
                          "direction": "column",
                          "style": {
                            "overflow": "hidden"
                          }
                        },
                        "type": "ia.container.flex"
                      }
                    ],
                    "meta": {
                      "name": "Control_Mode"
                    },
                    "position": {
                      "basis": "150px",
                      "shrink": 0
                    },
                    "props": {
                      "style": {
                        "overflow": "hidden"
                      }
                    },
                    "type": "ia.container.flex"
                  }
                ],
                "meta": {
                  "name": "control_expanded"
                },
                "position": {
                  "basis": "200px",
                  "shrink": 0
                },
                "propConfig": {
                  "position.display": {
                    "binding": {
                      "config": {
                        "path": "view.custom.lightControl"
                      },
                      "enabled": false,
                      "type": "property"
                    }
                  }
                },
                "props": {
                  "direction": "column",
                  "style": {
                    "marginBottom": 2,
                    "marginTop": 2,
                    "overflow": "hidden"
                  }
                },
                "type": "ia.container.flex"
              },
              {
                "children": [
                  {
                    "meta": {
                      "name": "Label_1"
                    },
                    "position": {
                      "basis": "24px",
                      "shrink": 0
                    },
                    "props": {
                      "style": {
                        "overflow": "hidden"
                      }
                    },
                    "type": "ia.display.label"
                  },
                  {
                    "events": {
                      "dom": {
                        "onClick": {
                          "config": {
                            "script": "\tself.view.custom.showAlarms \u003d False"
                          },
                          "scope": "G",
                          "type": "script"
                        }
                      }
                    },
                    "meta": {
                      "name": "Heading"
                    },
                    "position": {
                      "grow": 1,
                      "shrink": 0
                    },
                    "props": {
                      "style": {
                        "cursor": "pointer",
                        "overflow": "hidden",
                        "textAlign": "center",
                        "textTransform": "uppercase"
                      },
                      "text": "Alarms"
                    },
                    "type": "ia.display.label"
                  },
                  {
                    "children": [
                      {
                        "events": {
                          "dom": {
                            "onClick": {
                              "config": {
                                "script": "\ttagPath \u003d self.view.custom.deviceTagPath + \u0027/Alarm Reset CMD\u0027\n\tsystem.tag.writeBlocking([tagPath], [1])"
                              },
                              "scope": "G",
                              "type": "script"
                            }
                          }
                        },
                        "meta": {
                          "name": "Button"
                        },
                        "position": {
                          "basis": "80px"
                        },
                        "props": {
                          "style": {
                            "classes": "Input/Button/Body-normal Input/Button/Text",
                            "marginBottom": "5px",
                            "marginTop": "5px",
                            "overflow": "hidden"
                          },
                          "text": "reset"
                        },
                        "type": "ia.input.button"
                      }
                    ],
                    "meta": {
                      "name": "FlexContainer"
                    },
                    "position": {
                      "basis": "60px",
                      "display": false,
                      "shrink": 0
                    },
                    "props": {
                      "justify": "flex-end",
                      "style": {
                        "marginRight": 10,
                        "overflow": "hidden"
                      }
                    },
                    "type": "ia.container.flex"
                  },
                  {
                    "meta": {
                      "name": "Icon"
                    },
                    "position": {
                      "basis": "24px",
                      "shrink": 0
                    },
                    "propConfig": {
                      "props.path": {
                        "binding": {
                          "config": {
                            "path": ".../alarms_expanded.position.display"
                          },
                          "transforms": [
                            {
                              "fallback": null,
                              "inputType": "scalar",
                              "mappings": [
                                {
                                  "input": false,
                                  "output": "material/keyboard_arrow_up"
                                },
                                {
                                  "input": true,
                                  "output": "material/keyboard_arrow_down"
                                }
                              ],
                              "outputType": "scalar",
                              "type": "map"
                            }
                          ],
                          "type": "property"
                        }
                      }
                    },
                    "props": {
                      "style": {
                        "overflow": "hidden"
                      }
                    },
                    "type": "ia.display.icon"
                  }
                ],
                "events": {
                  "dom": {
                    "onClick": {
                      "config": {
                        "script": "\tpanelName \u003d self.getChild(\"Heading\").props.text + \u0027_expanded\u0027\n\tpanelName \u003d panelName.lower()\n\t\n\tself.getSibling(panelName).position.display \u003d not self.getSibling(panelName).position.display"
                      },
                      "scope": "G",
                      "type": "script"
                    }
                  }
                },
                "meta": {
                  "name": "alarms_header"
                },
                "position": {
                  "basis": "40px",
                  "shrink": 0
                },
                "props": {
                  "style": {
                    "classes": "UI/Text/Heading1",
                    "overflow": "hidden"
                  }
                },
                "type": "ia.container.flex"
              },
              {
                "meta": {
                  "name": "alarms_expanded"
                },
                "position": {
                  "shrink": 0
                },
                "propConfig": {
                  "props.params.deviceName": {
                    "binding": {
                      "config": {
                        "expression": "{view.params.deviceName}"
                      },
                      "type": "expr"
                    }
                  },
                  "props.params.deviceParentPath": {
                    "binding": {
                      "config": {
                        "path": "view.custom.sitePath"
                      },
                      "type": "property"
                    }
                  }
                },
                "props": {
                  "params": {
                    "controlEnable": true,
                    "show": {
                      "area": false,
                      "device": false
                    }
                  },
                  "path": "Shared/Templates/Devices/Control/Common/Alarms",
                  "style": {
                    "marginBottom": "5px",
                    "marginLeft": "5px",
                    "marginRight": "5px"
                  }
                },
                "type": "ia.display.view"
              }
            ],
            "meta": {
              "name": "Body"
            },
            "position": {
              "basis": "300px",
              "grow": 1
            },
            "props": {
              "direction": "column",
              "style": {
                "classes": "UI/Popups/ContentMargins",
                "overflow": "hidden"
              }
            },
            "type": "ia.container.flex"
          },
          {
            "events": {
              "dom": {
                "onClick": {
                  "config": {
                    "script": "\tself.getSibling(\"Info\").position.display \u003d not self.getSibling(\"Info\").position.display"
                  },
                  "scope": "G",
                  "type": "script"
                }
              }
            },
            "meta": {
              "name": "Info Icon"
            },
            "position": {
              "basis": "20px",
              "shrink": 0
            },
            "propConfig": {
              "position.display": {
                "binding": {
                  "config": {
                    "expression": "// Check user roles\r\ntry(hasRole(\u0027Administrator\u0027, {session.props.auth.user.userName}, \u0027default\u0027), false)"
                  },
                  "enabled": false,
                  "type": "expr"
                }
              }
            },
            "props": {
              "color": "#009BFF",
              "path": "material/info",
              "style": {
                "classes": "Input/Icon",
                "overflow": "hidden"
              }
            },
            "type": "ia.display.icon"
          },
          {
            "children": [
              {
                "meta": {
                  "name": "Label_2"
                },
                "position": {
                  "shrink": 0
                },
                "propConfig": {
                  "props.text": {
                    "binding": {
                      "config": {
                        "path": "view.custom.deviceTagPath"
                      },
                      "transforms": [
                        {
                          "expression": "\u0027Tag path: \u0027 + {value}",
                          "type": "expression"
                        }
                      ],
                      "type": "property"
                    }
                  }
                },
                "props": {
                  "style": {
                    "color": "var(--neutral-80)",
                    "fontSize": "8pt",
                    "fontWeight": "lighter",
                    "marginLeft": "5px",
                    "overflow": "hidden"
                  }
                },
                "type": "ia.display.label"
              }
            ],
            "meta": {
              "name": "Info"
            },
            "position": {
              "display": false,
              "shrink": 0
            },
            "props": {
              "direction": "column",
              "style": {
                "marginTop": "5px",
                "overflow": "hidden"
              }
            },
            "type": "ia.container.flex"
          }
        ],
        "meta": {
          "name": "FlexContainer"
        },
        "position": {
          "basis": "582px",
          "grow": 1
        },
        "props": {
          "direction": "column",
          "style": {
            "overflow": "hidden"
          }
        },
        "type": "ia.container.flex"
      },
      {
        "events": {
          "dom": {
            "onClick": {
              "config": {
                "script": "\tsystem.perspective.closePopup(self.view.custom.deviceTagPath)"
              },
              "scope": "G",
              "type": "script"
            }
          }
        },
        "meta": {
          "name": "Button"
        },
        "position": {
          "basis": "30px",
          "shrink": 0
        },
        "props": {
          "image": {
            "icon": {
              "path": "material/close"
            }
          },
          "style": {
            "borderBottomLeftRadius": 0,
            "borderBottomRightRadius": 0,
            "borderBottomStyle": "none",
            "borderLeftStyle": "none",
            "borderRightStyle": "none",
            "borderTopLeftRadius": 0,
            "borderTopRightRadius": 0,
            "classes": "Input/Button/Body-normal Input/Button/Colour/Normal",
            "overflow": "hidden"
          },
          "text": "Exit"
        },
        "type": "ia.input.button"
      }
    ],
    "meta": {
      "name": "root"
    },
    "props": {
      "direction": "column",
      "style": {
        "overflow": "hidden"
      }
    },
    "type": "ia.container.flex"
  }
}