{
  "custom": {
    "controlPopupId": "[default]Water Monitoring System/International/Test Pump Station/Flow Meter 5070-51_testCmd",
    "deviceDescription": null,
    "deviceTagPath": "[default]Water Monitoring System/International/Test Pump Station/Flow Meter 5070-51_test",
    "pens": [
      {
        "axis": "Instantaneous Flow",
        "data": {
          "aggregateMode": "default"
        },
        "display": {
          "breakLine": true,
          "interpolation": "curveLinear",
          "radius": 3,
          "styles": {
            "highlighted": {
              "fill": {
                "color": "#FC8D62",
                "opacity": 1
              },
              "stroke": {
                "color": "#FC8D62",
                "dashArray": 0,
                "opacity": 1,
                "width": 1
              }
            },
            "muted": {
              "fill": {
                "color": "#FC8D62",
                "opacity": 0.4
              },
              "stroke": {
                "color": "#FC8D62",
                "dashArray": 0,
                "opacity": 0.4,
                "width": 1
              }
            },
            "normal": {
              "fill": {
                "color": "#FC8D62",
                "opacity": 0.8
              },
              "stroke": {
                "color": "#FC8D62",
                "dashArray": 0,
                "opacity": 0.8,
                "width": 1
              }
            },
            "selected": {
              "fill": {
                "color": "#FC8D62",
                "opacity": 1
              },
              "stroke": {
                "color": "#FC8D62",
                "dashArray": 0,
                "opacity": 1,
                "width": 1
              }
            }
          },
          "type": "line"
        },
        "enabled": true,
        "name": "Instantaneous Flow",
        "plot": 0,
        "selectable": true,
        "visible": true
      },
      {
        "axis": "Total Usage",
        "data": {
          "aggregateMode": "default"
        },
        "display": {
          "breakLine": true,
          "interpolation": "curveLinear",
          "radius": 3,
          "styles": {
            "highlighted": {
              "fill": {
                "color": "#8DA0CB",
                "opacity": 1
              },
              "stroke": {
                "color": "#8DA0CB",
                "dashArray": 0,
                "opacity": 1,
                "width": 1
              }
            },
            "muted": {
              "fill": {
                "color": "#8DA0CB",
                "opacity": 0.4
              },
              "stroke": {
                "color": "#8DA0CB",
                "dashArray": 0,
                "opacity": 0.4,
                "width": 1
              }
            },
            "normal": {
              "fill": {
                "color": "#8DA0CB",
                "opacity": 0.8
              },
              "stroke": {
                "color": "#8DA0CB",
                "dashArray": 0,
                "opacity": 0.8,
                "width": 1
              }
            },
            "selected": {
              "fill": {
                "color": "#8DA0CB",
                "opacity": 1
              },
              "stroke": {
                "color": "#8DA0CB",
                "dashArray": 0,
                "opacity": 1,
                "width": 1
              }
            }
          },
          "type": "line"
        },
        "enabled": true,
        "name": "Net Flow Totaliser",
        "plot": 0,
        "selectable": true,
        "visible": true
      }
    ],
    "resetTagAvailable": false,
    "resetTagEnabled": true,
    "siteName": null,
    "sitePath": "[default]Water Monitoring System/International/Test Pump Station",
    "subArea": null
  },
  "params": {
    "deviceName": "Flow Meter 5070-51_test",
    "deviceParentPath": "[default]Water Monitoring System/International/Test Pump Station"
  },
  "propConfig": {
    "custom.controlPopupId": {
      "binding": {
        "config": {
          "expression": "{view.custom.deviceTagPath} + \"Cmd\""
        },
        "type": "expr"
      },
      "persistent": true
    },
    "custom.deviceDescription": {
      "binding": {
        "config": {
          "fallbackDelay": 2.5,
          "mode": "indirect",
          "references": {
            "deviceTagPath": "{view.custom.deviceTagPath}"
          },
          "tagPath": "{deviceTagPath}/Parameters.Description"
        },
        "type": "tag"
      },
      "persistent": true
    },
    "custom.deviceTagPath": {
      "binding": {
        "config": {
          "expression": "{view.params.deviceParentPath}+ \u0027/\u0027+{view.params.deviceName}"
        },
        "type": "expr"
      },
      "persistent": true
    },
    "custom.pens": {
      "persistent": true
    },
    "custom.pens[0].data.source": {
      "binding": {
        "config": {
          "expression": "{HistorySource} + {view.custom.deviceTagPath} + \u0027/Status Folder/Instantaneous Flow\u0027"
        },
        "transforms": [
          {
            "expression": "replace({value},\u0027[default]\u0027,\u0027\u0027)",
            "type": "expression"
          }
        ],
        "type": "expr"
      }
    },
    "custom.pens[1].data.source": {
      "binding": {
        "config": {
          "expression": "{HistorySource} + {view.custom.deviceTagPath} + \u0027/Status Folder/Net Flow Totaliser\u0027"
        },
        "transforms": [
          {
            "expression": "replace({value},\u0027[default]\u0027,\u0027\u0027)",
            "type": "expression"
          }
        ],
        "type": "expr"
      }
    },
    "custom.resetTagAvailable": {
      "binding": {
        "config": {
          "expression": "isAvailable (tag({view.custom.deviceTagPath}+\u0027/Command/Reset Totaliser Command\u0027))"
        },
        "type": "expr"
      },
      "persistent": true
    },
    "custom.siteName": {
      "binding": {
        "config": {
          "fallbackDelay": 2.5,
          "mode": "indirect",
          "references": {
            "deviceTagPath": "{view.custom.deviceTagPath}"
          },
          "tagPath": "{deviceTagPath}/Parameters.Alarm_ParentDevice"
        },
        "type": "tag"
      },
      "persistent": true
    },
    "custom.sitePath": {
      "binding": {
        "config": {
          "expression": "{view.params.deviceParentPath}"
        },
        "type": "expr"
      },
      "persistent": true
    },
    "custom.subArea": {
      "binding": {
        "config": {
          "fallbackDelay": 2.5,
          "mode": "indirect",
          "references": {
            "deviceTagPath": "{view.custom.deviceTagPath}"
          },
          "tagPath": "{deviceTagPath}/Parameters/Alarm_Area"
        },
        "type": "tag"
      },
      "persistent": true
    },
    "params.deviceName": {
      "paramDirection": "inout",
      "persistent": true
    },
    "params.deviceParentPath": {
      "paramDirection": "inout",
      "persistent": true
    }
  },
  "props": {
    "defaultSize": {
      "height": 540,
      "width": 362
    }
  },
  "root": {
    "children": [
      {
        "children": [
          {
            "children": [
              {
                "children": [
                  {
                    "meta": {
                      "name": "Label_1"
                    },
                    "position": {
                      "grow": 1
                    },
                    "propConfig": {
                      "props.text": {
                        "binding": {
                          "config": {
                            "expression": "tag({view.custom.deviceTagPath}+\u0027/Parameters.DeviceName\u0027) + \u0027 - \u0027 + {view.custom.deviceDescription}"
                          },
                          "type": "expr"
                        }
                      }
                    },
                    "props": {
                      "style": {
                        "color": "var(--neutral-20)",
                        "fontSize": "8pt",
                        "fontWeight": "bold",
                        "letterSpacing": "1px",
                        "textAlign": "center",
                        "textTransform": "uppercase"
                      }
                    },
                    "type": "ia.display.label"
                  },
                  {
                    "meta": {
                      "name": "Label_0"
                    },
                    "position": {
                      "grow": 1,
                      "shrink": 0
                    },
                    "propConfig": {
                      "props.text": {
                        "binding": {
                          "config": {
                            "expression": "{view.custom.subArea} + \u0027 - \u0027 + {view.custom.siteName}"
                          },
                          "transforms": [
                            {
                              "code": "\tnew_value \u003d value.replace(\"International \", \"\")\n\tdisplay_value \u003d new_value.replace(\"Domestic \", \"\")\n\treturn display_value",
                              "type": "script"
                            }
                          ],
                          "type": "expr"
                        }
                      }
                    },
                    "props": {
                      "style": {
                        "color": "var(--neutral-20)",
                        "fontSize": "10pt",
                        "fontStyle": "italic",
                        "fontWeight": "lighter",
                        "letterSpacing": "1px",
                        "marginBottom": "5px",
                        "textAlign": "center",
                        "textTransform": "uppercase"
                      }
                    },
                    "type": "ia.display.label"
                  }
                ],
                "meta": {
                  "name": "FlexContainer"
                },
                "position": {
                  "grow": 1,
                  "shrink": 0
                },
                "props": {
                  "direction": "column"
                },
                "type": "ia.container.flex"
              },
              {
                "children": [
                  {
                    "meta": {
                      "name": "Symbol_Double"
                    },
                    "position": {
                      "grow": 1
                    },
                    "propConfig": {
                      "props.params.alarmSummary.parentPath": {
                        "binding": {
                          "config": {
                            "path": "view.custom.deviceTagPath"
                          },
                          "type": "property"
                        }
                      },
                      "props.params.device.name": {
                        "binding": {
                          "config": {
                            "path": "view.params.deviceName"
                          },
                          "type": "property"
                        }
                      },
                      "props.params.device.parentPath": {
                        "binding": {
                          "config": {
                            "path": "view.custom.sitePath"
                          },
                          "type": "property"
                        }
                      }
                    },
                    "props": {
                      "params": {
                        "alarmSummary": {
                          "enabled": true
                        },
                        "device": {
                          "enabled": false
                        }
                      },
                      "path": "Shared/Alarms/Symbol"
                    },
                    "type": "ia.display.view"
                  }
                ],
                "meta": {
                  "name": "FlexContainer_1"
                },
                "position": {
                  "basis": "10%"
                },
                "propConfig": {
                  "position.display": {
                    "binding": {
                      "config": {
                        "fallbackDelay": 2.5,
                        "mode": "indirect",
                        "references": {
                          "deviceTagPath": "{view.custom.deviceTagPath}"
                        },
                        "tagPath": "{deviceTagPath}/Alarm Summary/Priority Counts/Active"
                      },
                      "transforms": [
                        {
                          "code": "\tif \tvalue \u003e 0:\n\t\tvalue \u003d 1\n\telse:\n\t\tvalue \u003d 0\n\t\t\n\treturn value",
                          "type": "script"
                        }
                      ],
                      "type": "tag"
                    }
                  }
                },
                "props": {
                  "style": {
                    "marginRight": "5px"
                  }
                },
                "type": "ia.container.flex"
              }
            ],
            "meta": {
              "name": "FlexContainer"
            },
            "position": {
              "basis": "0px",
              "grow": 1,
              "shrink": 0
            },
            "props": {
              "style": {
                "overflow": "hidden"
              }
            },
            "type": "ia.container.flex"
          }
        ],
        "meta": {
          "name": "Header"
        },
        "position": {
          "shrink": 0
        },
        "props": {
          "style": {
            "backgroundColor": "var(--neutral-80)",
            "borderBottomColor": "var(--neutral-100)",
            "borderBottomStyle": "solid",
            "borderBottomWidth": "1px",
            "overflow": "hidden"
          }
        },
        "type": "ia.container.flex"
      },
      {
        "children": [
          {
            "children": [
              {
                "children": [
                  {
                    "meta": {
                      "name": "Label"
                    },
                    "position": {
                      "basis": "45px"
                    },
                    "props": {
                      "style": {
                        "classes": "UI/Text/Heading2"
                      },
                      "text": "Analogue"
                    },
                    "type": "ia.display.label"
                  },
                  {
                    "meta": {
                      "name": "FlexRepeater_1"
                    },
                    "position": {
                      "basis": "80px"
                    },
                    "propConfig": {
                      "props.instances[0].tagParentPath": {
                        "binding": {
                          "config": {
                            "expression": "{view.custom.deviceTagPath} + \u0027/Set Points\u0027"
                          },
                          "type": "expr"
                        }
                      },
                      "props.instances[0].unitsOverride": {
                        "binding": {
                          "config": {
                            "expression": "tag ({view.custom.deviceTagPath} + \u0027/Status Folder/Instantaneous Flow.EngUnit\u0027)"
                          },
                          "type": "expr"
                        }
                      },
                      "props.instances[1].tagParentPath": {
                        "binding": {
                          "config": {
                            "expression": "{view.custom.deviceTagPath} + \u0027/Set Points\u0027"
                          },
                          "type": "expr"
                        }
                      },
                      "props.instances[1].unitsOverride": {
                        "binding": {
                          "config": {
                            "expression": "tag ({view.custom.deviceTagPath} + \u0027/Status Folder/Instantaneous Flow.EngUnit\u0027)"
                          },
                          "type": "expr"
                        }
                      }
                    },
                    "props": {
                      "direction": "column",
                      "elementPosition": {
                        "basis": "40px",
                        "grow": 0
                      },
                      "elementStyle": {
                        "margin": "1px"
                      },
                      "instances": [
                        {
                          "controlEnable": true,
                          "hideLabel": false,
                          "instancePosition": {},
                          "instanceStyle": {
                            "classes": ""
                          },
                          "labelOverride": "",
                          "setpointWidth": "100px",
                          "tagName": "High Flow Set Point",
                          "tagQuality": "Bad_NotFound(\"Path \u0027[default]Water Monitoring System/International/Test Pump Station/Flow Meter 5070-51_test/Set Points/High Flow Set Point.quality\u0027 not found.\")",
                          "unitsWidth": "40px",
                          "useDeviceRanges": false
                        },
                        {
                          "controlEnable": true,
                          "hideLabel": false,
                          "instancePosition": {},
                          "instanceStyle": {
                            "classes": ""
                          },
                          "labelOverride": "",
                          "setpointWidth": "100px",
                          "tagName": "Low Flow Set Point",
                          "tagQuality": "Bad_NotFound(\"Path \u0027[default]Water Monitoring System/International/Test Pump Station/Flow Meter 5070-51_test/Set Points/Low Flow Set Point.quality\u0027 not found.\")",
                          "unitsWidth": "40px",
                          "useDeviceRanges": false
                        }
                      ],
                      "path": "Shared/Templates/Display/Analogue Setpoint w Label",
                      "style": {
                        "overflow": "hidden"
                      },
                      "useDefaultViewHeight": false,
                      "useDefaultViewWidth": false
                    },
                    "type": "ia.display.flex-repeater"
                  },
                  {
                    "meta": {
                      "name": "FlexRepeater_2"
                    },
                    "position": {
                      "basis": "160px"
                    },
                    "propConfig": {
                      "props.instances[0].instanceStyle.display": {
                        "binding": {
                          "config": {
                            "expression": "if({this.props.instances[0].tagQuality}\u003d\"Good\", \u0027flex\u0027, \u0027none\u0027)"
                          },
                          "type": "expr"
                        }
                      },
                      "props.instances[0].tagParentPath": {
                        "binding": {
                          "config": {
                            "path": "view.custom.deviceTagPath"
                          },
                          "transforms": [
                            {
                              "expression": "{value} + \u0027/Status Folder\u0027",
                              "type": "expression"
                            }
                          ],
                          "type": "property"
                        }
                      },
                      "props.instances[1].instanceStyle.display": {
                        "binding": {
                          "config": {
                            "expression": "if({this.props.instances[1].tagQuality}\u003d\"Good\", \u0027flex\u0027, \u0027none\u0027)"
                          },
                          "type": "expr"
                        }
                      },
                      "props.instances[1].tagParentPath": {
                        "binding": {
                          "config": {
                            "path": "view.custom.deviceTagPath"
                          },
                          "transforms": [
                            {
                              "expression": "{value} + \u0027/Status Folder\u0027",
                              "type": "expression"
                            }
                          ],
                          "type": "property"
                        }
                      },
                      "props.instances[2].instanceStyle.display": {
                        "binding": {
                          "config": {
                            "expression": "if({this.props.instances[2].tagQuality}\u003d\"Good\", \u0027flex\u0027, \u0027none\u0027)"
                          },
                          "type": "expr"
                        }
                      },
                      "props.instances[2].tagParentPath": {
                        "binding": {
                          "config": {
                            "path": "view.custom.deviceTagPath"
                          },
                          "transforms": [
                            {
                              "expression": "{value} + \u0027/Status Folder\u0027",
                              "type": "expression"
                            }
                          ],
                          "type": "property"
                        }
                      },
                      "props.instances[3].instanceStyle.display": {
                        "binding": {
                          "config": {
                            "expression": "if({this.props.instances[3].tagQuality}\u003d\"Good\", \u0027flex\u0027, \u0027none\u0027)"
                          },
                          "type": "expr"
                        }
                      },
                      "props.instances[3].tagParentPath": {
                        "binding": {
                          "config": {
                            "path": "view.custom.deviceTagPath"
                          },
                          "transforms": [
                            {
                              "expression": "{value} + \u0027/Status Folder\u0027",
                              "type": "expression"
                            }
                          ],
                          "type": "property"
                        }
                      }
                    },
                    "props": {
                      "direction": "column",
                      "elementPosition": {
                        "basis": "40px",
                        "grow": 0
                      },
                      "elementStyle": {
                        "margin": "1px"
                      },
                      "instances": [
                        {
                          "hideLabel": false,
                          "instancePosition": {},
                          "instanceStyle": {
                            "classes": ""
                          },
                          "labelOverride": "",
                          "showUnitsInValue": true,
                          "tagName": "Instantaneous Flow",
                          "tagQuality": "Bad_NotFound(\"Path \u0027[default]Water Monitoring System/International/Test Pump Station/Flow Meter 5070-51_test/Status Folder/Instantaneous Flow.quality\u0027 not found.\")",
                          "unitsWidth": "40px",
                          "valueWidth": "100px"
                        },
                        {
                          "hideLabel": false,
                          "instancePosition": {},
                          "instanceStyle": {
                            "classes": ""
                          },
                          "labelOverride": "Total Usage",
                          "showUnitsInValue": true,
                          "tagName": "Net Flow Totaliser",
                          "tagQuality": "Bad_NotFound(\"Path \u0027[default]Water Monitoring System/International/Test Pump Station/Flow Meter 5070-51_test/Status Folder/Net Flow Totaliser.quality\u0027 not found.\")",
                          "unitsWidth": "40px",
                          "valueWidth": "150px"
                        },
                        {
                          "hideLabel": false,
                          "instancePosition": {},
                          "instanceStyle": {
                            "classes": ""
                          },
                          "labelOverride": "",
                          "showUnitsInValue": true,
                          "tagName": "Net Flow Day Totaliser",
                          "tagQuality": "Bad_NotFound(\"Path \u0027[default]Water Monitoring System/International/Test Pump Station/Flow Meter 5070-51_test/Status Folder/Net Flow Day Totaliser.quality\u0027 not found.\")",
                          "unitsWidth": "40px",
                          "valueWidth": "100px"
                        },
                        {
                          "hideLabel": false,
                          "instancePosition": {},
                          "instanceStyle": {
                            "classes": ""
                          },
                          "labelOverride": "",
                          "showUnitsInValue": true,
                          "tagName": "Net Flow Yesterday Totaliser",
                          "tagQuality": "Bad_NotFound(\"Path \u0027[default]Water Monitoring System/International/Test Pump Station/Flow Meter 5070-51_test/Status Folder/Net Flow Yesterday Totaliser.quality\u0027 not found.\")",
                          "unitsWidth": "40px",
                          "valueWidth": "100px"
                        }
                      ],
                      "path": "Shared/Templates/Display/Analogue Value w Label",
                      "style": {
                        "overflow": "hidden"
                      },
                      "useDefaultViewHeight": false,
                      "useDefaultViewWidth": false
                    },
                    "type": "ia.display.flex-repeater"
                  },
                  {
                    "meta": {
                      "name": "Label_1"
                    },
                    "position": {
                      "basis": "45px"
                    },
                    "propConfig": {
                      "meta.visible": {
                        "binding": {
                          "config": {
                            "path": "view.custom.resetTagAvailable"
                          },
                          "type": "property"
                        }
                      }
                    },
                    "props": {
                      "style": {
                        "classes": "UI/Text/Heading2"
                      },
                      "text": "Reset Totaliser"
                    },
                    "type": "ia.display.label"
                  },
                  {
                    "events": {
                      "component": {
                        "onActionPerformed": {
                          "config": {
                            "script": "\twidth \u003d self.page.props.dimensions.viewport.width\n\tprint(width)\n\tif width \u003e 1260:\n\t\tsystem.perspective.openPopup(self.view.custom.controlPopupId, \u0027Popups/HV/ppuConfirmAction\u0027, {\u0027deviceParentPath\u0027 : self.view.params.deviceParentPath, \u0027deviceName\u0027 : self.view.params.deviceName, \u0027command\u0027 : \u0027Reset Totaliser Command\u0027, \u0027onConfirm_WriteValue\u0027 : 1}, showCloseIcon \u003d False, draggable \u003d True)\n\telse:\n\t\tsystem.perspective.openPopup(self.view.custom.controlPopupId, \u0027Popups/HV/ppuConfirmAction\u0027, {\u0027deviceParentPath\u0027 : self.view.params.deviceParentPath, \u0027deviceName\u0027 : self.view.params.deviceName, \u0027command\u0027 : \u0027Reset Totaliser Command\u0027, \u0027onConfirm_WriteValue\u0027 : 1}, showCloseIcon \u003d False, draggable \u003d False)\t\t\t"
                          },
                          "scope": "G",
                          "type": "script"
                        }
                      }
                    },
                    "meta": {
                      "name": "Reset"
                    },
                    "position": {
                      "basis": "45px"
                    },
                    "propConfig": {
                      "meta.visible": {
                        "binding": {
                          "config": {
                            "path": "view.custom.resetTagAvailable"
                          },
                          "type": "property"
                        }
                      },
                      "props.enabled": {
                        "binding": {
                          "config": {
                            "expression": "//check if the user has got the required Security Level to enable the botton\r\n//try (\r\n//hasRole(\r\n//tag(\u0027Parameters/Security/1st Required Level for WMS Actions\u0027), //required roll name for the command\r\n//{session.props.auth.user.userName}, //current user\r\n//tag(\u0027Parameters/Security/Perspective Users Source Name\u0027)), //user source\r\n//false) //fallback\r\n//\r\ntry (\r\nisAuthorized (false, //check if one of following levels is authorized\r\ntag (\u0027Parameters/Security/1st Required Level for WMS Actions\u0027), tag (\u0027Parameters/Security/2nd Required Level for WMS Actions\u0027)),//\u0027Authenticated/Roles/Administrator\u0027, \u0027Authenticated/Roles/FTM Test Role\u0027,\r\nfalse) //fallback"
                          },
                          "type": "expr"
                        }
                      },
                      "props.style.classes": {
                        "binding": {
                          "config": {
                            "expression": "if({this.props.enabled} \u003d true,\r\n\t\u0027Input/Button/Body-normal Input/Button/Colour/Normal\u0027,\r\n\t\u0027UI/Icon/Button-faded\u0027\r\n)"
                          },
                          "enabled": false,
                          "type": "expr"
                        }
                      }
                    },
                    "props": {
                      "primary": false,
                      "style": {
                        "classes": "Input/Button/Body-normal Input/Button/Text",
                        "marginBottom": 5,
                        "marginLeft": 125,
                        "marginRight": 125,
                        "marginTop": 5
                      },
                      "text": "Reset"
                    },
                    "type": "ia.input.button"
                  }
                ],
                "meta": {
                  "name": "FlexContainer"
                },
                "position": {
                  "basis": "375px"
                },
                "props": {
                  "direction": "column"
                },
                "type": "ia.container.flex"
              },
              {
                "meta": {
                  "name": "FlexContainer_0"
                },
                "position": {
                  "basis": "0px",
                  "grow": 1
                },
                "type": "ia.container.flex"
              },
              {
                "events": {
                  "dom": {
                    "onClick": {
                      "config": {
                        "script": "\tself.getSibling(\"Info\").position.display \u003d not self.getSibling(\"Info\").position.display"
                      },
                      "scope": "G",
                      "type": "script"
                    }
                  }
                },
                "meta": {
                  "name": "Info Icon"
                },
                "position": {
                  "basis": "20px",
                  "shrink": 0
                },
                "props": {
                  "color": "#009BFF",
                  "path": "material/info",
                  "style": {
                    "classes": "Input/Icon",
                    "overflow": "hidden"
                  }
                },
                "type": "ia.display.icon"
              },
              {
                "children": [
                  {
                    "meta": {
                      "name": "Label_2"
                    },
                    "position": {
                      "shrink": 0
                    },
                    "propConfig": {
                      "props.text": {
                        "binding": {
                          "config": {
                            "path": "view.custom.deviceTagPath"
                          },
                          "transforms": [
                            {
                              "expression": "\u0027Tag path: \u0027 + {value} + \"\\n\"+\r\n\u0027Interface: \u0027  + tag({view.custom.deviceTagPath} + \u0027/Parameters.FlowMeterAMSinterface\u0027) + \"\\n\"+\r\n\u0027Flow Meter Type: \u0027 + tag({view.custom.deviceTagPath} + \u0027/Parameters.FlowMeterType\u0027)",
                              "type": "expression"
                            }
                          ],
                          "type": "property"
                        }
                      }
                    },
                    "props": {
                      "style": {
                        "color": "var(--neutral-80)",
                        "fontSize": "8pt",
                        "fontWeight": "lighter",
                        "marginLeft": "5px",
                        "overflow": "hidden",
                        "whiteSpace": "pre-wrap"
                      }
                    },
                    "type": "ia.display.label"
                  }
                ],
                "meta": {
                  "name": "Info"
                },
                "position": {
                  "display": false,
                  "shrink": 0
                },
                "props": {
                  "direction": "column",
                  "style": {
                    "marginTop": "5px",
                    "overflow": "hidden"
                  }
                },
                "type": "ia.container.flex"
              }
            ],
            "meta": {
              "name": "Analogues"
            },
            "props": {
              "direction": "column",
              "style": {
                "classes": "UI/Popups/ContentMargins"
              }
            },
            "type": "ia.container.flex"
          },
          {
            "children": [
              {
                "events": {
                  "component": {
                    "onActionPerformed": {
                      "config": {
                        "draggable": true,
                        "id": "pwMGOKRj",
                        "modal": false,
                        "overlayDismiss": false,
                        "resizable": true,
                        "showCloseIcon": true,
                        "type": "open",
                        "viewParams": {
                          "deviceName": "{view.params.deviceName}",
                          "deviceParentPath": "{view.params.deviceParentPath}",
                          "pens": "{view.custom.pens}"
                        },
                        "viewPath": "Popups/Trend Popup",
                        "viewportBound": false
                      },
                      "scope": "C",
                      "type": "popup"
                    }
                  }
                },
                "meta": {
                  "name": "Button"
                },
                "position": {
                  "basis": "40px"
                },
                "props": {
                  "image": {
                    "icon": {
                      "path": "material/show_chart"
                    }
                  },
                  "style": {
                    "classes": "Input/Button/Body-normal Input/Button/Colour/Normal"
                  },
                  "text": "Historical Trends"
                },
                "type": "ia.input.button"
              },
              {
                "custom": {
                  "tags": [
                    {
                      "aggregate": "Average",
                      "alias": "Instantaneous Flow"
                    },
                    {
                      "aggregate": "Average",
                      "alias": "Total Usage"
                    }
                  ]
                },
                "meta": {
                  "name": "TimeSeriesChart"
                },
                "position": {
                  "basis": "400px",
                  "grow": 1
                },
                "propConfig": {
                  "custom.tags[0].path": {
                    "binding": {
                      "config": {
                        "expression": "{view.custom.deviceTagPath}+ \u0027/Status Folder/Instantaneous Flow\u0027"
                      },
                      "type": "expr"
                    }
                  },
                  "custom.tags[1].path": {
                    "binding": {
                      "config": {
                        "expression": "{view.custom.deviceTagPath}+ \u0027/Status Folder/Net Flow Totaliser\u0027"
                      },
                      "type": "expr"
                    }
                  },
                  "props.series[0].data": {
                    "binding": {
                      "config": {
                        "aggregate": "MinMax",
                        "avoidScanClassValidation": true,
                        "dateRange": {
                          "mostRecent": "1",
                          "mostRecentUnits": "HOUR"
                        },
                        "enableValueCache": true,
                        "ignoreBadQuality": false,
                        "polling": {
                          "enabled": true,
                          "rate": "1"
                        },
                        "preventInterpolation": false,
                        "returnFormat": "Wide",
                        "returnSize": {
                          "numRows": "100",
                          "type": "FIXED"
                        },
                        "tags": "{this.custom.tags}",
                        "valueFormat": "DATASET"
                      },
                      "type": "tag-history"
                    }
                  }
                },
                "props": {
                  "legend": {
                    "visible": true
                  },
                  "plots": [
                    {
                      "axes": [
                        {
                          "alignment": "left",
                          "grid": {
                            "color": "",
                            "dashArray": 0,
                            "opacity": 0.9,
                            "style": {
                              "classes": ""
                            },
                            "visible": false
                          },
                          "label": {
                            "font": {
                              "color": "",
                              "size": 10
                            },
                            "offset": 0,
                            "style": {
                              "classes": ""
                            },
                            "text": "Instantaneous Flow",
                            "visible": true
                          },
                          "max": "",
                          "min": "",
                          "name": "Flow",
                          "style": {
                            "classes": ""
                          },
                          "tick": {
                            "color": "",
                            "count": "Auto",
                            "label": {
                              "font": {
                                "color": "",
                                "size": 10
                              },
                              "format": "Auto",
                              "style": {
                                "classes": ""
                              }
                            },
                            "style": {
                              "classes": ""
                            }
                          },
                          "width": 60
                        }
                      ],
                      "markers": [],
                      "relativeWeight": 1,
                      "trends": [
                        {
                          "axis": "Instantaneous Flow",
                          "baselines": [],
                          "breakLine": true,
                          "columns": [],
                          "interpolation": "curveLinear",
                          "radius": 2,
                          "series": "Flow",
                          "stack": true,
                          "type": "line",
                          "visible": true
                        }
                      ]
                    }
                  ],
                  "series": [
                    {
                      "name": "Flow"
                    }
                  ]
                },
                "type": "ia.chart.timeseries"
              }
            ],
            "meta": {
              "name": "Trends"
            },
            "position": {
              "tabIndex": 1
            },
            "props": {
              "direction": "column"
            },
            "type": "ia.container.flex"
          },
          {
            "meta": {
              "name": "alarms_expanded"
            },
            "position": {
              "tabIndex": 2
            },
            "propConfig": {
              "props.params.deviceName": {
                "binding": {
                  "config": {
                    "expression": "{view.params.deviceName}"
                  },
                  "type": "expr"
                }
              },
              "props.params.deviceParentPath": {
                "binding": {
                  "config": {
                    "path": "view.custom.sitePath"
                  },
                  "type": "property"
                }
              }
            },
            "props": {
              "params": {
                "controlEnable": true,
                "show": {
                  "area": false,
                  "device": false
                }
              },
              "path": "Shared/Templates/Devices/Control/Common/Alarms",
              "style": {
                "marginBottom": "5px",
                "marginLeft": "5px",
                "marginRight": "5px"
              }
            },
            "type": "ia.display.view"
          }
        ],
        "meta": {
          "name": "TabContainer"
        },
        "position": {
          "basis": "400px",
          "grow": 1
        },
        "props": {
          "menuType": "modern",
          "style": {
            "classes": "UI/Popups/Background"
          },
          "tabStyle": {
            "active": {
              "fontSize": 12
            },
            "inactive": {
              "fontSize": 12
            }
          },
          "tabs": [
            "Analogues",
            "Trends",
            "Alarms"
          ]
        },
        "type": "ia.container.tab"
      },
      {
        "events": {
          "dom": {
            "onClick": {
              "config": {
                "script": "\tsystem.perspective.closePopup(self.view.custom.deviceTagPath)"
              },
              "scope": "G",
              "type": "script"
            }
          }
        },
        "meta": {
          "name": "Button"
        },
        "position": {
          "basis": "30px",
          "shrink": 0
        },
        "props": {
          "image": {
            "icon": {
              "path": "material/close"
            }
          },
          "style": {
            "borderBottomLeftRadius": 0,
            "borderBottomRightRadius": 0,
            "borderBottomStyle": "none",
            "borderLeftStyle": "none",
            "borderRightStyle": "none",
            "borderTopLeftRadius": 0,
            "borderTopRightRadius": 0,
            "classes": "Input/Button/Body-normal Input/Button/Colour/Normal"
          },
          "text": "Exit"
        },
        "type": "ia.input.button"
      }
    ],
    "meta": {
      "name": "root"
    },
    "props": {
      "direction": "column",
      "style": {
        "classes": "UI/Popups/Background"
      }
    },
    "type": "ia.container.flex"
  }
}