{
  "custom": {},
  "params": {},
  "props": {
    "defaultSize": {
      "height": 1040,
      "width": 1920
    }
  },
  "root": {
    "children": [
      {
        "meta": {
          "name": "T2 Overview"
        },
        "position": {
          "height": 999.96,
          "width": 1920,
          "y": 40.04
        },
        "props": {
          "fit": {
            "mode": "fill"
          },
          "source": "/system/images/Domestic/T2 Overview.svg"
        },
        "type": "ia.display.image"
      },
      {
        "meta": {
          "name": "Top Strip"
        },
        "position": {
          "height": 40.04,
          "width": 1920
        },
        "props": {
          "params": {
            "siteAlarmsVisible": false,
            "sitePath": "Domestic/T2"
          },
          "path": "Navigation/Top Strip"
        },
        "type": "ia.display.view"
      }
    ],
    "meta": {
      "name": "root"
    },
    "propConfig": {
      "props.aspectRatio": {
        "binding": {
          "config": {
            "expression": "{view.props.defaultSize.width} + \u0027:\u0027 + {view.props.defaultSize.height}"
          },
          "type": "expr"
        }
      }
    },
    "props": {
      "style": {
        "classes": "UI/Pages/Background",
        "overflow": "hidden"
      }
    },
    "type": "ia.container.coord"
  }
}